fuss/__init__.py
fuss/main.py
pyfuss-0.0.2.dist-info/LICENSE
pyfuss-0.0.2.dist-info/METADATA
pyfuss-0.0.2.dist-info/WHEEL
pyfuss-0.0.2.dist-info/top_level.txt
pyfuss-0.0.2.dist-info/RECORD
