Metadata-Version: 2.1
Name: pyfuss
Version: 0.0.2
Summary: Fast Uniform Style String in Python
Author: Cure-X
Author-email: admin@cure-x.net
License: GPL3
Keywords: fuss,pyfuss
License-File: LICENSE
